uacme_desec.py
uacme_desec-1.2.1.dist-info/METADATA
uacme_desec-1.2.1.dist-info/WHEEL
uacme_desec-1.2.1.dist-info/entry_points.txt
uacme_desec-1.2.1.dist-info/top_level.txt
uacme_desec-1.2.1.dist-info/RECORD
