Metadata-Version: 2.1
Name: uacme-desec
Version: 1.2.1
Summary: uacme-desec - An UACME hook for deSEC
Author-email: Hugo Rodrigues <hugo.rodrigues@openbit.tech>
Project-URL: Homepage, https://codeberg.org/openbit/uacme-desec
Project-URL: Issues, https://codeberg.org/openbit/uacme-desec/issues
Classifier: Programming Language :: Python :: 3
Classifier: License :: OSI Approved :: MIT License
Classifier: Operating System :: OS Independent
Requires-Python: >=3.10
